{
  "db_name": "PostgreSQL",
  "query": "\n            INSERT INTO mint_ops (uid, kid, minted, bill_id, blob)\n            VALUES ($1, $2, $3, $4, $5)\n            ON CONFLICT (uid) DO NOTHING\n            RETURNING uid\n            ",
  "describe": {
    "columns": [
      {
        "ordinal": 0,
        "name": "uid",
        "type_info": "Uuid"
      }
    ],
    "parameters": {
      "Left": [
        "Uuid",
        "Text",
        "Int8",
        "Text",
        "Jsonb"
      ]
    },
    "nullable": [
      false
    ]
  },
  "hash": "8995a12719bae432e909fc1aeca784ec213042e8e1b7f2288b7f80501e734bcd"
}
